MANIFEST.in
README.rst
setup.py
surcharge/__init__.py
surcharge/cli.py
surcharge/core.py
surcharge.egg-info/PKG-INFO
surcharge.egg-info/SOURCES.txt
surcharge.egg-info/dependency_links.txt
surcharge.egg-info/entry_points.txt
surcharge.egg-info/requires.txt
surcharge.egg-info/top_level.txt
surcharge/libs/__init__.py
surcharge/libs/docopt.py