Metadata-Version: 1.1
Name: surcharge
Version: 0.9.1
Summary: Surcharge is a tool for benchmarking your web server
Home-page: https://github.com/Lujeni/Surcharge
Author: Lujeni
Author-email: julien@thebault.co
License: UNKNOWN
Platform: UNKNOWN
Classifier: Programming Language :: Python :: 2.7
Classifier: Development Status :: 1 - Planning
Classifier: License :: OSI Approved :: BSD License
Classifier: Natural Language :: English
Classifier: Operating System :: Unix
